{
  "openapi": "3.0.1",
  "info": {
    "title": "Web.API - João Mendes",
    "version": "2.0"
  },
  "paths": {
    "/api/v2/employee": {
      "post": {
        "tags": [
          "Funcionario"
        ],
        "requestBody": {
          "content": {
            "multipart/form-data": {
              "schema": {
                "type": "object",
                "properties": {
                  "Nome": {
                    "type": "string"
                  },
                  "Idade": {
                    "type": "integer",
                    "format": "int32"
                  },
                  "Cargo": {
                    "type": "string"
                  }
                }
              },
              "encoding": {
                "Nome": {
                  "style": "form"
                },
                "Idade": {
                  "style": "form"
                },
                "Cargo": {
                  "style": "form"
                }
              }
            }
          }
        },
        "responses": {
          "200": {
            "description": "OK"
          }
        }
      },
      "get": {
        "tags": [
          "Funcionario"
        ],
        "parameters": [
          {
            "name": "pageNumber",
            "in": "query",
            "schema": {
              "type": "integer",
              "format": "int32"
            }
          },
          {
            "name": "pageQuantity",
            "in": "query",
            "schema": {
              "type": "integer",
              "format": "int32"
            }
          }
        ],
        "responses": {
          "200": {
            "description": "OK"
          }
        }
      }
    },
    "/api/v2/employee/{id}": {
      "get": {
        "tags": [
          "Funcionario"
        ],
        "parameters": [
          {
            "name": "id",
            "in": "path",
            "required": true,
            "schema": {
              "type": "integer",
              "format": "int32"
            }
          }
        ],
        "responses": {
          "200": {
            "description": "OK"
          }
        }
      }
    }
  },
  "components": {
    "securitySchemes": {
      "Bearer": {
        "type": "apiKey",
        "name": "Authorization",
        "in": "header"
      }
    }
  },
  "security": [
    {
      "Bearer": [ ]
    }
  ]
}